[
{
"caseNumber": "02426880",
"uuid": "81f5b9e6-2819-4c5b-8ce3-3c8ba037596e",
"checksum": "b597f189103e2780567ee1063f486cc43885acd9df948410c9d46b9cca2c4471",
"createdDate": "2020-03-09T07:24:45Z",
"createdBy": "Yeshi, Chetan",
"fileName": "sosreport-3050.tar (2).xz",
"fileType": "application/x-xz",
"id": "a092i000000QubiAAC",
"isArchived": false,
"isDeprecated": false,
"isPrivate": false,
"lastModifiedDate": "2020-03-09T07:24:45Z",
"link": "https://access.qa.redhat.com/hydra/rest/cases/02426880/attachments/81f5b9e6-2819-4c5b-8ce3-3c8ba037596e",
"modifiedBy": "Yeshi, Chetan",
"size": 1305,
"sizeKB": 1.27,
"downloadRestricted": false
},
{
"caseNumber": "02426880",
"uuid": "771b432c-bb45-4fe5-aca7-cec0edc923de",
"checksum": "b10c4225423f59df153dac66d5ead18e7ad7c80bd71b10673705964d455c9490",
"createdDate": "2020-03-09T07:28:44Z",
"createdBy": "Yeshi, Chetan",
"fileName": "sosreport_router_invalid_cert.tar.gz",
"fileType": "application/x-gtar",
"id": "a092i000000QuewAAC",
"isArchived": false,
"isDeprecated": false,
"isPrivate": false,
"lastModifiedDate": "2020-03-09T07:28:44Z",
"link": "https://access.qa.redhat.com/hydra/rest/cases/02426880/attachments/771b432c-bb45-4fe5-aca7-cec0edc923de",
"modifiedBy": "Yeshi, Chetan",
"size": 910694400,
"sizeKB": 889350,
"downloadRestricted": false
},
{
"caseNumber": "02426880",
"uuid": "e3dd410b-a674-4a8f-af00-1b575b77bebd",
"checksum": "52f51f574956fc6b9dbc1b5ff38d18487a7593a54801803998cfb25bdedec7ba",
"createdDate": "2020-03-09T07:27:16Z",
"createdBy": "Yeshi, Chetan",
"fileName": "sosreport-3050.tar (1).xz",
"fileType": "application/x-xz",
"id": "a092i000000QuerAAC",
"isArchived": false,
"isDeprecated": false,
"isPrivate": false,
"lastModifiedDate": "2020-03-09T07:27:16Z",
"link": "https://access.qa.redhat.com/hydra/rest/cases/02426880/attachments/e3dd410b-a674-4a8f-af00-1b575b77bebd",
"modifiedBy": "Yeshi, Chetan",
"size": 272900344,
"sizeKB": 266504.24,
"downloadRestricted": false
},
{
"caseNumber": "02426880",
"uuid": "f1b9f747-d70c-4413-a86d-d9a5fc9e6b67",
"checksum": "52f51f574956fc6b9dbc1b5ff38d18487a7593a54801803998cfb25bdedec7ba",
"createdDate": "2020-03-09T07:27:13Z",
"createdBy": "Yeshi, Chetan",
"fileName": "sosreport-3050.tar.xz",
"fileType": "application/x-xz",
"id": "a092i000000QuemAAC",
"isArchived": false,
"isDeprecated": false,
"isPrivate": false,
"lastModifiedDate": "2020-03-09T07:27:13Z",
"link": "https://access.qa.redhat.com/hydra/rest/cases/02426880/attachments/f1b9f747-d70c-4413-a86d-d9a5fc9e6b67",
"modifiedBy": "Yeshi, Chetan",
"size": 272900344,
"sizeKB": 266504.24,
"downloadRestricted": false
},
{
"caseNumber": "02426880",
"uuid": "26f0798a-c821-448c-9788-4631269b4a77",
"checksum": "f558f2ef8761ae53280bef4c747927ddd4d5c100a96dfbc50fc84e697775832e",
"createdDate": "2020-03-09T07:27:10Z",
"createdBy": "Yeshi, Chetan",
"fileName": "sosreport-3050-no-incident.tar.xz",
"fileType": "application/x-xz",
"id": "a092i000000QuehAAC",
"isArchived": false,
"isDeprecated": false,
"isPrivate": false,
"lastModifiedDate": "2020-03-09T07:27:10Z",
"link": "https://access.qa.redhat.com/hydra/rest/cases/02426880/attachments/26f0798a-c821-448c-9788-4631269b4a77",
"modifiedBy": "Yeshi, Chetan",
"size": 248392976,
"sizeKB": 242571.26,
"downloadRestricted": false
},
{
"caseNumber": "02426880",
"uuid": "329c9c98-24b2-45aa-bcce-5f94509530a6",
"checksum": "8a101792e3b3505b8d3749bf0887a457915dd02275d91b2b84bacc555a43b4b7",
"createdDate": "2020-03-09T07:27:03Z",
"createdBy": "Yeshi, Chetan",
"fileName": "sosreport-3557-incident-key.tar.xz",
"fileType": "application/x-xz",
"id": "a092i000000QuecAAC",
"isArchived": false,
"isDeprecated": false,
"isPrivate": false,
"lastModifiedDate": "2020-03-09T07:27:03Z",
"link": "https://access.qa.redhat.com/hydra/rest/cases/02426880/attachments/329c9c98-24b2-45aa-bcce-5f94509530a6",
"modifiedBy": "Yeshi, Chetan",
"size": 234590460,
"sizeKB": 229092.24,
"downloadRestricted": false
},
{
"caseNumber": "02426880",
"uuid": "bf8ac059-da28-4fc2-8fa6-4ad1b6893c7c",
"checksum": "76cb212ba6eb7c451a45ad904b056f54bd7d485c00f41f498b909aeeb7773742",
"createdDate": "2020-03-09T07:26:47Z",
"createdBy": "Yeshi, Chetan",
"fileName": "sosreport-p652900.02305109-20190130172252.tar.xz",
"fileType": "application/x-xz",
"id": "a092i000000QueXAAS",
"isArchived": false,
"isDeprecated": false,
"isPrivate": false,
"lastModifiedDate": "2020-03-09T07:26:47Z",
"link": "https://access.qa.redhat.com/hydra/rest/cases/02426880/attachments/bf8ac059-da28-4fc2-8fa6-4ad1b6893c7c",
"modifiedBy": "Yeshi, Chetan",
"size": 89478508,
"sizeKB": 87381.35,
"downloadRestricted": false
},
{
"caseNumber": "02426880",
"uuid": "756b1a5a-3e0e-4822-ba4e-66f622db87f8",
"checksum": "7d468fa40ea3c92833b06480b5060a64e7d0d9d08a6f0d9559ea5412b84bc285",
"createdDate": "2020-03-09T07:26:44Z",
"createdBy": "Yeshi, Chetan",
"fileName": "sosreport-s2tldora03n02-2019-01-03-jpwmtwg.tar(1).xz",
"fileType": "application/x-xz",
"id": "a092i000000QueSAAS",
"isArchived": false,
"isDeprecated": false,
"isPrivate": false,
"lastModifiedDate": "2020-03-09T07:26:44Z",
"link": "https://access.qa.redhat.com/hydra/rest/cases/02426880/attachments/756b1a5a-3e0e-4822-ba4e-66f622db87f8",
"modifiedBy": "Yeshi, Chetan",
"size": 68786472,
"sizeKB": 67174.28,
"downloadRestricted": false
},
{
"caseNumber": "02426880",
"uuid": "32ae8b4e-1fc2-45df-b841-bcaf34946fa3",
"checksum": "5349998fb58cfac51b9a203fbfe2c40a7b4c296bc84e69e331f84167aa735662",
"createdDate": "2020-03-09T07:26:40Z",
"createdBy": "Yeshi, Chetan",
"fileName": "sosreport-0752-telstar-02512442-2019-11-18-wlpjrgr.tar.xz",
"fileType": "application/x-xz",
"id": "a092i000000QueNAAS",
"isArchived": false,
"isDeprecated": false,
"isPrivate": false,
"lastModifiedDate": "2020-03-09T07:26:40Z",
"link": "https://access.qa.redhat.com/hydra/rest/cases/02426880/attachments/32ae8b4e-1fc2-45df-b841-bcaf34946fa3",
"modifiedBy": "Yeshi, Chetan",
"size": 105557604,
"sizeKB": 103083.59,
"downloadRestricted": false
},
{
"caseNumber": "02426880",
"uuid": "86b3dd18-8f8a-42ef-861a-ae0c6fbdead5",
"checksum": "13c3a3978ef87243b6716845e198b19dd2b017b75073d4946df09bd206b60c1d",
"createdDate": "2020-03-09T07:26:37Z",
"createdBy": "Yeshi, Chetan",
"fileName": "sosreport-ocp-health.tar.xz",
"fileType": "application/x-gtar",
"id": "a092i000000QueIAAS",
"isArchived": false,
"isDeprecated": false,
"isPrivate": false,
"lastModifiedDate": "2020-03-09T07:26:37Z",
"link": "https://access.qa.redhat.com/hydra/rest/cases/02426880/attachments/86b3dd18-8f8a-42ef-861a-ae0c6fbdead5",
"modifiedBy": "Yeshi, Chetan",
"size": 136038400,
"sizeKB": 132850,
"downloadRestricted": false
},
{
"caseNumber": "02426880",
"uuid": "641d50e7-6457-446d-ba6a-5b99834d03f1",
"checksum": "6b6966a5b3601cbf622b733eb23baa6a7cc4ad12c830eacbcac5ccf38d1fc9f0",
"createdDate": "2020-03-09T07:26:35Z",
"createdBy": "Yeshi, Chetan",
"fileName": "sosreport-network_teamd.tar.xz",
"fileType": "application/x-gtar",
"id": "a092i000000QueDAAS",
"isArchived": false,
"isDeprecated": false,
"isPrivate": false,
"lastModifiedDate": "2020-03-09T07:26:35Z",
"link": "https://access.qa.redhat.com/hydra/rest/cases/02426880/attachments/641d50e7-6457-446d-ba6a-5b99834d03f1",
"modifiedBy": "Yeshi, Chetan",
"size": 123801600,
"sizeKB": 120900,
"downloadRestricted": false
},
{
"caseNumber": "02426880",
"uuid": "66ef05fc-428e-441e-b14e-2397051f9234",
"checksum": "bafab07824d70203948e0d52d816b2ad802a93195014ddf9d792df90d6bce7a6",
"createdDate": "2020-03-09T07:26:32Z",
"createdBy": "Yeshi, Chetan",
"fileName": "sosreport-db-rhev-h1.rhev.com-20190524170743.tar.xz",
"fileType": "application/x-xz",
"id": "a092i000000Que8AAC",
"isArchived": false,
"isDeprecated": false,
"isPrivate": false,
"lastModifiedDate": "2020-03-09T07:26:32Z",
"link": "https://access.qa.redhat.com/hydra/rest/cases/02426880/attachments/66ef05fc-428e-441e-b14e-2397051f9234",
"modifiedBy": "Yeshi, Chetan",
"size": 89257056,
"sizeKB": 87165.09,
"downloadRestricted": false
},
{
"caseNumber": "02426880",
"uuid": "d5964506-355e-4faa-ac82-085d6aab65ea",
"checksum": "639a1ad39e394dbd5b04358f6a7f9f68d98d51431c53c725f5b777fe189237a8",
"createdDate": "2020-03-09T07:26:29Z",
"createdBy": "Yeshi, Chetan",
"fileName": "sosreport-PetrosTsehay.02404907-20190614121222.tar.xz",
"fileType": "application/x-xz",
"id": "a092i000000Que3AAC",
"isArchived": false,
"isDeprecated": false,
"isPrivate": false,
"lastModifiedDate": "2020-03-09T07:26:29Z",
"link": "https://access.qa.redhat.com/hydra/rest/cases/02426880/attachments/d5964506-355e-4faa-ac82-085d6aab65ea",
"modifiedBy": "Yeshi, Chetan",
"size": 51347852,
"sizeKB": 50144.38,
"downloadRestricted": false
},
{
"caseNumber": "02426880",
"uuid": "cf4c6100-6725-4ceb-b7aa-075f8b737803",
"checksum": "072544fb27909b31d4ac2d3fc7a8533e339fd75138bbee46aa5d12ce52cff4aa",
"createdDate": "2020-03-09T07:26:26Z",
"createdBy": "Yeshi, Chetan",
"fileName": "sosreport-AvinashYada.02510736-20191105043054.tar.xz",
"fileType": "application/x-xz",
"id": "a092i000000QudyAAC",
"isArchived": false,
"isDeprecated": false,
"isPrivate": false,
"lastModifiedDate": "2020-03-09T07:26:26Z",
"link": "https://access.qa.redhat.com/hydra/rest/cases/02426880/attachments/cf4c6100-6725-4ceb-b7aa-075f8b737803",
"modifiedBy": "Yeshi, Chetan",
"size": 34749544,
"sizeKB": 33935.1,
"downloadRestricted": false
},
{
"caseNumber": "02426880",
"uuid": "8582128b-2c88-465e-bc2a-c14c1435f1b4",
"checksum": "159a4c7bd43645a16b48cb01c7863999a87e29d51f6190c8eb858b8e889c33fa",
"createdDate": "2020-03-09T07:26:24Z",
"createdBy": "Yeshi, Chetan",
"fileName": "sosreport-crpra92a0156-2019-10-16-paopfsr.tar.xz",
"fileType": "application/x-xz",
"id": "a092i000000QudtAAC",
"isArchived": false,
"isDeprecated": false,
"isPrivate": false,
"lastModifiedDate": "2020-03-09T07:26:24Z",
"link": "https://access.qa.redhat.com/hydra/rest/cases/02426880/attachments/8582128b-2c88-465e-bc2a-c14c1435f1b4",
"modifiedBy": "Yeshi, Chetan",
"size": 27222416,
"sizeKB": 26584.39,
"downloadRestricted": false
},
{
"caseNumber": "02426880",
"uuid": "85c500f5-7b63-4fd5-ac63-782a6217abce",
"checksum": "7336258c12a8860e80f68da0788c668bd12b0d4da1aef067bf54176dd72e012f",
"createdDate": "2020-03-09T07:26:13Z",
"createdBy": "Yeshi, Chetan",
"fileName": "sosreport-sisvr02458-20190625100104.tar.xz",
"fileType": "application/x-xz",
"id": "a092i000000QudoAAC",
"isArchived": false,
"isDeprecated": false,
"isPrivate": false,
"lastModifiedDate": "2020-03-09T07:26:13Z",
"link": "https://access.qa.redhat.com/hydra/rest/cases/02426880/attachments/85c500f5-7b63-4fd5-ac63-782a6217abce",
"modifiedBy": "Yeshi, Chetan",
"size": 24231268,
"sizeKB": 23663.34,
"downloadRestricted": false
},
{
"caseNumber": "02426880",
"uuid": "b03c51ee-2285-4470-b939-7ba661545acf",
"checksum": "7d468fa40ea3c92833b06480b5060a64e7d0d9d08a6f0d9559ea5412b84bc285",
"createdDate": "2020-03-09T07:26:11Z",
"createdBy": "Yeshi, Chetan",
"fileName": "sosreport-s2tldora03n02-2019-01-03-jpwmtwg.tar (1).xz",
"fileType": "application/x-xz",
"id": "a092i000000QudjAAC",
"isArchived": false,
"isDeprecated": false,
"isPrivate": false,
"lastModifiedDate": "2020-03-09T07:26:11Z",
"link": "https://access.qa.redhat.com/hydra/rest/cases/02426880/attachments/b03c51ee-2285-4470-b939-7ba661545acf",
"modifiedBy": "Yeshi, Chetan",
"size": 68786472,
"sizeKB": 67174.28,
"downloadRestricted": false
},
{
"caseNumber": "02426880",
"uuid": "e3ed90dc-ed84-495c-94f7-360b19dbe81e",
"checksum": "f1f09a3e832d555177c01b0588073759eccf3893a2b1246de6d7a4dc0f877fab",
"createdDate": "2020-03-09T07:26:04Z",
"createdBy": "Yeshi, Chetan",
"fileName": "sosreport-ban.02383749-20190524184916.tar.xz",
"fileType": "application/x-xz",
"id": "a092i000000QudeAAC",
"isArchived": false,
"isDeprecated": false,
"isPrivate": false,
"lastModifiedDate": "2020-03-09T07:26:04Z",
"link": "https://access.qa.redhat.com/hydra/rest/cases/02426880/attachments/e3ed90dc-ed84-495c-94f7-360b19dbe81e",
"modifiedBy": "Yeshi, Chetan",
"size": 32672784,
"sizeKB": 31907.01,
"downloadRestricted": false
},
{
"caseNumber": "02426880",
"uuid": "5382a1d9-b840-4a41-82e8-fbb882141110",
"checksum": "deeeab33c5c8d84f4ec92665caf51ab863219ab5f423398dc7e6b84ad47b8266",
"createdDate": "2020-03-09T07:26:00Z",
"createdBy": "Yeshi, Chetan",
"fileName": "sosreport-sldbsp0003-02538429-2019-12-19-fsiefmh.tar.xz",
"fileType": "application/x-xz",
"id": "a092i000000QudZAAS",
"isArchived": false,
"isDeprecated": false,
"isPrivate": false,
"lastModifiedDate": "2020-03-09T07:26:00Z",
"link": "https://access.qa.redhat.com/hydra/rest/cases/02426880/attachments/5382a1d9-b840-4a41-82e8-fbb882141110",
"modifiedBy": "Yeshi, Chetan",
"size": 23112504,
"sizeKB": 22570.8,
"downloadRestricted": false
},
{
"caseNumber": "02426880",
"uuid": "94717b2a-3d84-4ff7-8425-99baa02d5d40",
"checksum": "e6fb63e6dc1c09233ecb6bd181f8500ae4f4b0d4d817ae400a65696917763861",
"createdDate": "2020-03-09T07:25:58Z",
"createdBy": "Yeshi, Chetan",
"fileName": "sosreport-cpt2-dpdk-totp-02486718-2019-10-10-gslwttj.tar.xz",
"fileType": "application/x-xz",
"id": "a092i000000QudUAAS",
"isArchived": false,
"isDeprecated": false,
"isPrivate": false,
"lastModifiedDate": "2020-03-09T07:25:58Z",
"link": "https://access.qa.redhat.com/hydra/rest/cases/02426880/attachments/94717b2a-3d84-4ff7-8425-99baa02d5d40",
"modifiedBy": "Yeshi, Chetan",
"size": 63105600,
"sizeKB": 61626.56,
"downloadRestricted": false
},
{
"caseNumber": "02426880",
"uuid": "68dd229c-2009-4fb5-bc47-1653421b59ac",
"checksum": "e5defad9d219afc64ccbdb3d50124447204fd3dd0aa7b36f7a7ae1b32988b4fc",
"createdDate": "2020-03-09T07:25:54Z",
"createdBy": "Yeshi, Chetan",
"fileName": "sosreport-sat6-qpidd-courrpt.tar.xz",
"fileType": "application/x-xz",
"id": "a092i000000QudPAAS",
"isArchived": false,
"isDeprecated": false,
"isPrivate": false,
"lastModifiedDate": "2020-03-09T07:25:54Z",
"link": "https://access.qa.redhat.com/hydra/rest/cases/02426880/attachments/68dd229c-2009-4fb5-bc47-1653421b59ac",
"modifiedBy": "Yeshi, Chetan",
"size": 34258384,
"sizeKB": 33455.45,
"downloadRestricted": false
},
{
"caseNumber": "02426880",
"uuid": "9472c2d8-81ca-4b07-a0ce-034aebf328d0",
"checksum": "34a54bb80817c3c65fa785d03068fa64e05e746448bc2059e72d60966c8e9042",
"createdDate": "2020-03-09T07:25:52Z",
"createdBy": "Yeshi, Chetan",
"fileName": "sosreport-e954275-20171128043247.tar.xz",
"fileType": "application/x-xz",
"id": "a092i000000QudKAAS",
"isArchived": false,
"isDeprecated": false,
"isPrivate": false,
"lastModifiedDate": "2020-03-09T07:25:52Z",
"link": "https://access.qa.redhat.com/hydra/rest/cases/02426880/attachments/9472c2d8-81ca-4b07-a0ce-034aebf328d0",
"modifiedBy": "Yeshi, Chetan",
"size": 41054428,
"sizeKB": 40092.21,
"downloadRestricted": false
},
{
"caseNumber": "02426880",
"uuid": "a5866094-0441-4abd-b428-dbb84078490b",
"checksum": "fb2c2e84d3a68fb3a4c88ccc75a3b7be91773bacae2c6e67f968b0ab01d4e9ab",
"createdDate": "2020-03-09T07:26:18Z",
"createdBy": "Yeshi, Chetan",
"fileName": "sosreport-3557-2.tar.xz",
"fileType": "application/x-xz",
"id": "a092i000000QudGAAS",
"isArchived": false,
"isDeprecated": false,
"isPrivate": false,
"lastModifiedDate": "2020-03-09T07:26:18Z",
"link": "https://access.qa.redhat.com/hydra/rest/cases/02426880/attachments/a5866094-0441-4abd-b428-dbb84078490b",
"modifiedBy": "Yeshi, Chetan",
"size": 18385232,
"sizeKB": 17954.32,
"downloadRestricted": false
},
{
"caseNumber": "02426880",
"uuid": "728721ac-0d7f-4560-90d3-1eb7fa4d35de",
"checksum": "d2b2b1ea10fcc2a0289d08bcd3a16dd7e2c95756059fd6427c3c69412a3d3353",
"createdDate": "2020-03-09T07:25:47Z",
"createdBy": "Yeshi, Chetan",
"fileName": "sosreport-p-l-min-node1.itella.net.02542897-20191217150532.tar.xz",
"fileType": "application/x-xz",
"id": "a092i000000QudFAAS",
"isArchived": false,
"isDeprecated": false,
"isPrivate": false,
"lastModifiedDate": "2020-03-09T07:25:47Z",
"link": "https://access.qa.redhat.com/hydra/rest/cases/02426880/attachments/728721ac-0d7f-4560-90d3-1eb7fa4d35de",
"modifiedBy": "Yeshi, Chetan",
"size": 12960936,
"sizeKB": 12657.16,
"downloadRestricted": false
},
{
"caseNumber": "02426880",
"uuid": "cfdd89a3-c0e5-43af-bc39-34c8f54159fe",
"checksum": "b8e3fbbc6aac667358887dd6beb5b0f81d14c4c4fccd16f86e99c14654eb381f",
"createdDate": "2020-03-09T07:26:20Z",
"createdBy": "Yeshi, Chetan",
"fileName": "sosreport-portville802-2019-07-30-wtxknmy.tar.xz",
"fileType": "application/x-xz",
"id": "a092i000000QudCAAS",
"isArchived": false,
"isDeprecated": false,
"isPrivate": false,
"lastModifiedDate": "2020-03-09T07:26:20Z",
"link": "https://access.qa.redhat.com/hydra/rest/cases/02426880/attachments/cfdd89a3-c0e5-43af-bc39-34c8f54159fe",
"modifiedBy": "Yeshi, Chetan",
"size": 38340776,
"sizeKB": 37442.16,
"downloadRestricted": false
},
{
"caseNumber": "02426880",
"uuid": "4355749d-0a4a-48dc-8c89-29af5ce007ed",
"checksum": "70f714cbb6ef8f1655556b9fda5631013ba854793659447435e0635438f4427b",
"createdDate": "2020-03-09T07:26:06Z",
"createdBy": "Yeshi, Chetan",
"fileName": "sosreport-ansible-ocb.xz",
"fileType": "application/x-xz",
"id": "a092i000000QudBAAS",
"isArchived": false,
"isDeprecated": false,
"isPrivate": false,
"lastModifiedDate": "2020-03-09T07:26:06Z",
"link": "https://access.qa.redhat.com/hydra/rest/cases/02426880/attachments/4355749d-0a4a-48dc-8c89-29af5ce007ed",
"modifiedBy": "Yeshi, Chetan",
"size": 22508672,
"sizeKB": 21981.12,
"downloadRestricted": false
},
{
"caseNumber": "02426880",
"uuid": "d04b71f2-1ef2-46a2-8838-f219cd85cedd",
"checksum": "48f64fb7401f8e0a5685f4b48dac737ae960af2c304a66ec1867891047276fe1",
"createdDate": "2020-03-09T07:25:45Z",
"createdBy": "Yeshi, Chetan",
"fileName": "sosreport-undercloud-cfme-02564689-2020-01-20-hszmbqu.tar.xz",
"fileType": "application/x-xz",
"id": "a092i000000QudAAAS",
"isArchived": false,
"isDeprecated": false,
"isPrivate": false,
"lastModifiedDate": "2020-03-09T07:25:45Z",
"link": "https://access.qa.redhat.com/hydra/rest/cases/02426880/attachments/d04b71f2-1ef2-46a2-8838-f219cd85cedd",
"modifiedBy": "Yeshi, Chetan",
"size": 15540036,
"sizeKB": 15175.81,
"downloadRestricted": false
},
{
"caseNumber": "02426880",
"uuid": "362a5b32-bba0-4d00-a7fa-52c38b1ab021",
"checksum": "3616bae0f01ec8107f90f3079f00394430e90ba622b9178b70d134b6d80be167",
"createdDate": "2020-03-09T07:25:41Z",
"createdBy": "Yeshi, Chetan",
"fileName": "sosreport-3738.tar.xz",
"fileType": "application/x-xz",
"id": "a092i000000Qud5AAC",
"isArchived": false,
"isDeprecated": false,
"isPrivate": false,
"lastModifiedDate": "2020-03-09T07:25:41Z",
"link": "https://access.qa.redhat.com/hydra/rest/cases/02426880/attachments/362a5b32-bba0-4d00-a7fa-52c38b1ab021",
"modifiedBy": "Yeshi, Chetan",
"size": 24270840,
"sizeKB": 23701.99,
"downloadRestricted": false
},
{
"caseNumber": "02426880",
"uuid": "3fd46ed5-cc1d-431d-909f-fbae2d2f4e79",
"checksum": "368a5d6c09cc56bd8f6e60cf9e6827efde19cb1832525f15aa9c3a5177eb4015",
"createdDate": "2020-03-09T07:25:38Z",
"createdBy": "Yeshi, Chetan",
"fileName": "sosreport-b3vpromgapp01-2019-05-16-ajqjbmm.tar.xz",
"fileType": "application/x-xz",
"id": "a092i000000Qud0AAC",
"isArchived": false,
"isDeprecated": false,
"isPrivate": false,
"lastModifiedDate": "2020-03-09T07:25:38Z",
"link": "https://access.qa.redhat.com/hydra/rest/cases/02426880/attachments/3fd46ed5-cc1d-431d-909f-fbae2d2f4e79",
"modifiedBy": "Yeshi, Chetan",
"size": 22722668,
"sizeKB": 22190.1,
"downloadRestricted": false
},
{
"caseNumber": "02426880",
"uuid": "e533e4ad-ce30-4147-a3ee-774d946a0d85",
"checksum": "954f06c3cd6d73c4ba62d23ba8e5bef8d95b3173d4ea16c883ba76ca088810d6",
"createdDate": "2020-03-09T07:25:33Z",
"createdBy": "Yeshi, Chetan",
"fileName": "sosreport-DDPPDOCN02.02397925-20191019040007.tar.xz",
"fileType": "application/x-xz",
"id": "a092i000000QucvAAC",
"isArchived": false,
"isDeprecated": false,
"isPrivate": false,
"lastModifiedDate": "2020-03-09T07:25:33Z",
"link": "https://access.qa.redhat.com/hydra/rest/cases/02426880/attachments/e533e4ad-ce30-4147-a3ee-774d946a0d85",
"modifiedBy": "Yeshi, Chetan",
"size": 24749004,
"sizeKB": 24168.94,
"downloadRestricted": false
},
{
"caseNumber": "02426880",
"uuid": "a3a09c5b-1ad3-40f0-8171-9a1ea08ed2ce",
"checksum": "ee10a0ccdc393cfae2563ff1d17ae7485d1c1a5bae3ec59ba666c77b4595ea9a",
"createdDate": "2020-03-09T07:25:31Z",
"createdBy": "Yeshi, Chetan",
"fileName": "sosreport-fdcgcg-racld13p.eur.nsroot.net.02529780-20191202131001.tar.xz",
"fileType": "application/x-xz",
"id": "a092i000000QucqAAC",
"isArchived": false,
"isDeprecated": false,
"isPrivate": false,
"lastModifiedDate": "2020-03-09T07:25:31Z",
"link": "https://access.qa.redhat.com/hydra/rest/cases/02426880/attachments/a3a09c5b-1ad3-40f0-8171-9a1ea08ed2ce",
"modifiedBy": "Yeshi, Chetan",
"size": 16177460,
"sizeKB": 15798.3,
"downloadRestricted": false
},
{
"caseNumber": "02426880",
"uuid": "3d25fb0b-49d2-40e0-9ef8-3a98bc7fbc0f",
"checksum": "7cd3b810cc964cbb2fa111c6e9f7115a37970dce3cc2204f029ed4a8cb8c5eca",
"createdDate": "2020-03-09T07:25:28Z",
"createdBy": "Yeshi, Chetan",
"fileName": "sosreport-feng-20190501080900.tar.xz",
"fileType": "application/x-xz",
"id": "a092i000000QuclAAC",
"isArchived": false,
"isDeprecated": false,
"isPrivate": false,
"lastModifiedDate": "2020-03-09T07:25:28Z",
"link": "https://access.qa.redhat.com/hydra/rest/cases/02426880/attachments/3d25fb0b-49d2-40e0-9ef8-3a98bc7fbc0f",
"modifiedBy": "Yeshi, Chetan",
"size": 12911520,
"sizeKB": 12608.9,
"downloadRestricted": false
},
{
"caseNumber": "02426880",
"uuid": "03d3fd42-4f48-4298-a1e9-34841016c900",
"checksum": "c5cda743c67e44713691a5e4bcd3f1b546eec07e5bf9fb9a80da32d06ca8cc9f",
"createdDate": "2020-03-09T07:25:25Z",
"createdBy": "Yeshi, Chetan",
"fileName": "sosreport-zs-dorapld01.zs.local-20191010065750.tar.xz",
"fileType": "application/x-xz",
"id": "a092i000000QucgAAC",
"isArchived": false,
"isDeprecated": false,
"isPrivate": false,
"lastModifiedDate": "2020-03-09T07:25:25Z",
"link": "https://access.qa.redhat.com/hydra/rest/cases/02426880/attachments/03d3fd42-4f48-4298-a1e9-34841016c900",
"modifiedBy": "Yeshi, Chetan",
"size": 16062412,
"sizeKB": 15685.94,
"downloadRestricted": false
},
{
"caseNumber": "02426880",
"uuid": "e42c4798-4421-4a19-86ea-ed37810a097b",
"checksum": "030e1a54eb241a6d8cea200e0bfa5bb88df680b308873e6b14cf21bbda6dc0fe",
"createdDate": "2020-03-09T07:25:22Z",
"createdBy": "Yeshi, Chetan",
"fileName": "sosreport-ucl000lab5-warn.tar.xz",
"fileType": "application/x-xz",
"id": "a092i000000QucbAAC",
"isArchived": false,
"isDeprecated": false,
"isPrivate": false,
"lastModifiedDate": "2020-03-09T07:25:22Z",
"link": "https://access.qa.redhat.com/hydra/rest/cases/02426880/attachments/e42c4798-4421-4a19-86ea-ed37810a097b",
"modifiedBy": "Yeshi, Chetan",
"size": 14051268,
"sizeKB": 13721.94,
"downloadRestricted": false
},
{
"caseNumber": "02426880",
"uuid": "beb74102-1a25-4265-a74e-095688afa86c",
"checksum": "827b841681b0a0909cd6ad33eab0a87a63cddb7ea756fb38802d55c892ab5556",
"createdDate": "2020-03-09T07:25:16Z",
"createdBy": "Yeshi, Chetan",
"fileName": "sosreport-CoreApp1.gtb-finacle.com.02465588DD-20191017094025.tar.xz",
"fileType": "application/x-xz",
"id": "a092i000000QucWAAS",
"isArchived": false,
"isDeprecated": false,
"isPrivate": false,
"lastModifiedDate": "2020-03-09T07:25:16Z",
"link": "https://access.qa.redhat.com/hydra/rest/cases/02426880/attachments/beb74102-1a25-4265-a74e-095688afa86c",
"modifiedBy": "Yeshi, Chetan",
"size": 18250652,
"sizeKB": 17822.9,
"downloadRestricted": false
},
{
"caseNumber": "02426880",
"uuid": "38907fe0-e0a5-46e8-8d50-361ca064534f",
"checksum": "3f3382eaf77dd02a409a91069f610dfd763c26bdfab37916f99f060a64d0e311",
"createdDate": "2020-03-09T07:25:13Z",
"createdBy": "Yeshi, Chetan",
"fileName": "sosreport-3557-1.tar.xz",
"fileType": "application/x-xz",
"id": "a092i000000QucRAAS",
"isArchived": false,
"isDeprecated": false,
"isPrivate": false,
"lastModifiedDate": "2020-03-09T07:25:13Z",
"link": "https://access.qa.redhat.com/hydra/rest/cases/02426880/attachments/38907fe0-e0a5-46e8-8d50-361ca064534f",
"modifiedBy": "Yeshi, Chetan",
"size": 18379024,
"sizeKB": 17948.26,
"downloadRestricted": false
},
{
"caseNumber": "02426880",
"uuid": "d5dc2225-6f75-4d8c-8d79-2243ee2c6a59",
"checksum": "fd65aaf2370dc14fc96a7ba5071c2688c91aeab3845643cd988f1cb82da3a457",
"createdDate": "2020-03-09T07:25:10Z",
"createdBy": "Yeshi, Chetan",
"fileName": "sosreport-dayrhejnkp001.enterprisenet.org.CASE02390838-20190524221348.tar.xz",
"fileType": "application/x-xz",
"id": "a092i000000QucMAAS",
"isArchived": false,
"isDeprecated": false,
"isPrivate": false,
"lastModifiedDate": "2020-03-09T07:25:10Z",
"link": "https://access.qa.redhat.com/hydra/rest/cases/02426880/attachments/d5dc2225-6f75-4d8c-8d79-2243ee2c6a59",
"modifiedBy": "Yeshi, Chetan",
"size": 11215352,
"sizeKB": 10952.49,
"downloadRestricted": false
},
{
"caseNumber": "02426880",
"uuid": "173fbbb0-94c9-49d4-a3af-dd2154554297",
"checksum": "afa15f83e064744f42c66af4fee57355e0b966b5ab4a1f35225c1ddce89a3925",
"createdDate": "2020-03-09T07:25:06Z",
"createdBy": "Yeshi, Chetan",
"fileName": "sosreport-GIvey.02503628-20191025145227.tar.xz",
"fileType": "application/x-xz",
"id": "a092i000000QucHAAS",
"isArchived": false,
"isDeprecated": false,
"isPrivate": false,
"lastModifiedDate": "2020-03-09T07:25:06Z",
"link": "https://access.qa.redhat.com/hydra/rest/cases/02426880/attachments/173fbbb0-94c9-49d4-a3af-dd2154554297",
"modifiedBy": "Yeshi, Chetan",
"size": 12786696,
"sizeKB": 12487,
"downloadRestricted": false
},
{
"caseNumber": "02426880",
"uuid": "f16f526a-2cfb-4cb7-93cf-55ba50fdc1f6",
"checksum": "86ced29884c81c82b044e61813d03bf8cce8edd98671af6a0e2748b95436f0d3",
"createdDate": "2020-03-09T07:25:04Z",
"createdBy": "Yeshi, Chetan",
"fileName": "sosreport-lvlorp04.americold.com-20191202073516.tar.xz",
"fileType": "application/x-xz",
"id": "a092i000000QucCAAS",
"isArchived": false,
"isDeprecated": false,
"isPrivate": false,
"lastModifiedDate": "2020-03-09T07:25:04Z",
"link": "https://access.qa.redhat.com/hydra/rest/cases/02426880/attachments/f16f526a-2cfb-4cb7-93cf-55ba50fdc1f6",
"modifiedBy": "Yeshi, Chetan",
"size": 14089380,
"sizeKB": 13759.16,
"downloadRestricted": false
},
{
"caseNumber": "02426880",
"uuid": "afd00b30-9b99-4985-8299-57913e9c648d",
"checksum": "540dda3821ae3dacb4aeff2bfa89543fb68a745e4db8b5333c2a2f9e92cd92fa",
"createdDate": "2020-03-09T07:24:59Z",
"createdBy": "Yeshi, Chetan",
"fileName": "sosreport-jbucksbaum-20180214161155.tar.xz",
"fileType": "application/x-xz",
"id": "a092i000000Quc7AAC",
"isArchived": false,
"isDeprecated": false,
"isPrivate": false,
"lastModifiedDate": "2020-03-09T07:24:59Z",
"link": "https://access.qa.redhat.com/hydra/rest/cases/02426880/attachments/afd00b30-9b99-4985-8299-57913e9c648d",
"modifiedBy": "Yeshi, Chetan",
"size": 17028056,
"sizeKB": 16628.96,
"downloadRestricted": false
},
{
"caseNumber": "02426880",
"uuid": "b95119bb-a616-4082-be0f-b7f018ad9016",
"checksum": "0f586221f1ed23a42acd1f4d2b8d74bcdfc10f416bb3ec7b6801a7c895a6e165",
"createdDate": "2020-03-09T07:24:57Z",
"createdBy": "Yeshi, Chetan",
"fileName": "sosreport-jcrook.02192105-20180928144921.tar.xz",
"fileType": "application/x-xz",
"id": "a092i000000Quc2AAC",
"isArchived": false,
"isDeprecated": false,
"isPrivate": false,
"lastModifiedDate": "2020-03-09T07:24:57Z",
"link": "https://access.qa.redhat.com/hydra/rest/cases/02426880/attachments/b95119bb-a616-4082-be0f-b7f018ad9016",
"modifiedBy": "Yeshi, Chetan",
"size": 9686644,
"sizeKB": 9459.61,
"downloadRestricted": false
},
{
"caseNumber": "02426880",
"uuid": "90fd0da9-bb65-4d60-8887-43b0bd6fdf47",
"checksum": "f4d59cac862a11f0d46378993ca48eac3d1807cc89f89154d205ae21bbf421bb",
"createdDate": "2020-03-09T07:24:53Z",
"createdBy": "Yeshi, Chetan",
"fileName": "sosreport-sqlts01-20190729133257.tar.xz",
"fileType": "application/x-xz",
"id": "a092i000000QubxAAC",
"isArchived": false,
"isDeprecated": false,
"isPrivate": false,
"lastModifiedDate": "2020-03-09T07:24:53Z",
"link": "https://access.qa.redhat.com/hydra/rest/cases/02426880/attachments/90fd0da9-bb65-4d60-8887-43b0bd6fdf47",
"modifiedBy": "Yeshi, Chetan",
"size": 11888188,
"sizeKB": 11609.55,
"downloadRestricted": false
},
{
"caseNumber": "02426880",
"uuid": "776ab6b5-6308-49f9-8002-50ff5531d4b4",
"checksum": "632d92e59ce877391bcbe6fb3162ea6d654bc7cd716ea8cbaa7e9ad6a0df7b1b",
"createdDate": "2020-03-09T07:24:51Z",
"createdBy": "Yeshi, Chetan",
"fileName": "sosreport-HCLT-PC5224-1-02491648-2019-10-10-uzksxem.tar.xz",
"fileType": "application/x-xz",
"id": "a092i000000QubsAAC",
"isArchived": false,
"isDeprecated": false,
"isPrivate": false,
"lastModifiedDate": "2020-03-09T07:24:51Z",
"link": "https://access.qa.redhat.com/hydra/rest/cases/02426880/attachments/776ab6b5-6308-49f9-8002-50ff5531d4b4",
"modifiedBy": "Yeshi, Chetan",
"size": 9629784,
"sizeKB": 9404.08,
"downloadRestricted": false
},
{
"caseNumber": "02426880",
"uuid": "83b73bb7-b769-42ae-b7c9-706e0680afc5",
"checksum": "3d3b094752adf80d7ee5b38ad6f1304513b11526f568dcb773e70b8022ffb625",
"createdDate": "2020-03-09T07:24:47Z",
"createdBy": "Yeshi, Chetan",
"fileName": "soscleaner-1414612077254698.tar.gz",
"fileType": "application/gzip",
"id": "a092i000000QubnAAC",
"isArchived": false,
"isDeprecated": false,
"isPrivate": false,
"lastModifiedDate": "2020-03-09T07:24:47Z",
"link": "https://access.qa.redhat.com/hydra/rest/cases/02426880/attachments/83b73bb7-b769-42ae-b7c9-706e0680afc5",
"modifiedBy": "Yeshi, Chetan",
"size": 1190,
"sizeKB": 1.16,
"downloadRestricted": false
},
{
"caseNumber": "02426880",
"uuid": "6e917cce-9196-40be-be4d-7e34cee81135",
"checksum": "cd1ad4080f6378b3a6d9bddff1c7eebea1414b67fbbbd89d1f39252a01dd21b7",
"createdDate": "2020-03-09T07:25:19Z",
"createdBy": "Yeshi, Chetan",
"fileName": "sosreport-z08svmq02-20190525103330-979f.tar.xz",
"fileType": "application/x-xz",
"id": "a092i000000QubjAAC",
"isArchived": false,
"isDeprecated": false,
"isPrivate": false,
"lastModifiedDate": "2020-03-09T07:25:18Z",
"link": "https://access.qa.redhat.com/hydra/rest/cases/02426880/attachments/6e917cce-9196-40be-be4d-7e34cee81135",
"modifiedBy": "Yeshi, Chetan",
"size": 11596680,
"sizeKB": 11324.88,
"downloadRestricted": false
},
{
"caseNumber": "02426880",
"uuid": "c7bc801b-36b3-4e13-834c-f6ae6503993e",
"checksum": "0b78627494580436f7098a09cef3433b8c3359147dfa992b6fb99523da27dddc",
"createdDate": "2020-01-15T14:57:34Z",
"createdBy": "Yeshi, Chetan",
"fileName": "pic.jpg",
"fileType": "image/jpeg",
"id": "a092i000000M3s9AAC",
"isArchived": false,
"isDeprecated": false,
"isPrivate": false,
"lastModifiedDate": "2020-01-15T14:57:34Z",
"link": "https://access.qa.redhat.com/hydra/rest/cases/02426880/attachments/c7bc801b-36b3-4e13-834c-f6ae6503993e",
"modifiedBy": "Yeshi, Chetan",
"size": 1151773,
"sizeKB": 1124.77,
"downloadRestricted": false
},
{
"caseNumber": "02426880",
"uuid": "798e587b-7c2e-47fa-b434-143c4ec410a4",
"checksum": "0b78627494580436f7098a09cef3433b8c3359147dfa992b6fb99523da27dddc",
"createdDate": "2020-01-15T14:56:05Z",
"createdBy": "Yeshi, Chetan",
"fileName": "pic.jpg",
"fileType": "image/jpeg",
"id": "a092i000000M3s4AAC",
"isArchived": false,
"isDeprecated": false,
"isPrivate": false,
"lastModifiedDate": "2020-01-15T14:56:05Z",
"link": "https://access.qa.redhat.com/hydra/rest/cases/02426880/attachments/798e587b-7c2e-47fa-b434-143c4ec410a4",
"modifiedBy": "Yeshi, Chetan",
"size": 1151773,
"sizeKB": 1124.77,
"downloadRestricted": false
},
{
"caseNumber": "02426880",
"uuid": "798e587b-7c2e-47fa-b434-143c4ec410a4",
"checksum": "0b78627494580436f7098a09cef3433b8c3359147dfa992b6fb99523da27dddc",
"createdDate": "2020-01-15T14:56:03Z",
"createdBy": "Yeshi, Chetan",
"fileName": "pic.jpg",
"fileType": "image/jpeg",
"id": "a092i000000M3rzAAC",
"isArchived": false,
"isDeprecated": false,
"isPrivate": false,
"lastModifiedDate": "2020-01-15T14:56:03Z",
"link": "https://access.qa.redhat.com/hydra/rest/cases/02426880/attachments/798e587b-7c2e-47fa-b434-143c4ec410a4",
"modifiedBy": "Yeshi, Chetan",
"size": 1151773,
"sizeKB": 1124.77,
"downloadRestricted": false
},
{
"caseNumber": "02426880",
"uuid": "cd83e164-73d4-413b-8e19-5f4499ee59d7",
"checksum": "00bd25f9063cf4ee18a34dbdbad6f9b224b5f496e4f6ae01ceca7079c6b485b9",
"createdDate": "2020-01-14T08:53:26Z",
"createdBy": "Yeshi, Chetan",
"description": "private attcahment",
"fileName": "cde",
"fileType": "text/plain",
"id": "a092i000000M2B8AAK",
"isArchived": false,
"isDeprecated": false,
"isPrivate": true,
"lastModifiedDate": "2020-01-14T08:56:06Z",
"link": "https://access.qa.redhat.com/hydra/rest/cases/02426880/attachments/cd83e164-73d4-413b-8e19-5f4499ee59d7",
"modifiedBy": "Yeshi, Chetan",
"size": 18711,
"sizeKB": 18.27,
"downloadRestricted": false
},
{
"caseNumber": "02426880",
"uuid": "b4de3fa9-9f35-41df-b668-c39308eeb111",
"checksum": "6007602c6c020fda7b9fcce25cfd5297c8a5260e91bf95701ac604c0248c2e4a",
"createdDate": "2020-01-14T08:52:57Z",
"createdBy": "Yeshi, Chetan",
"description": "public attachment",
"fileName": "f1.txt",
"fileType": "application/octet-stream",
"id": "a092i000000M2ApAAK",
"isArchived": false,
"isDeprecated": false,
"isPrivate": false,
"lastModifiedDate": "2020-01-14T08:52:57Z",
"link": "https://access.qa.redhat.com/hydra/rest/cases/02426880/attachments/b4de3fa9-9f35-41df-b668-c39308eeb111",
"modifiedBy": "Yeshi, Chetan",
"size": 14000000,
"sizeKB": 13671.87,
"downloadRestricted": false
},
{
"caseNumber": "02426880",
"uuid": "954408ea-0091-4eb8-b806-5ce47a6b8d81",
"checksum": "ba79e0f7d7e7045a739b20936e06873bab3a3f96eb1b6a46d6bc8a6703202a3c",
"createdDate": "2020-01-14T08:49:20Z",
"createdBy": "Yeshi, Chetan",
"fileName": "ChineseName_你好世界.png",
"fileType": "image/png",
"id": "a092i000000M2AyAAK",
"isArchived": false,
"isDeprecated": false,
"isPrivate": true,
"lastModifiedDate": "2020-01-14T08:49:20Z",
"link": "https://access.qa.redhat.com/hydra/rest/cases/02426880/attachments/954408ea-0091-4eb8-b806-5ce47a6b8d81",
"modifiedBy": "Yeshi, Chetan",
"size": 1936056,
"sizeKB": 1890.67,
"downloadRestricted": false
},
{
"caseNumber": "02426880",
"uuid": "da3ccd10-b204-4688-9009-01fd0710d448",
"checksum": "010f60d2927a35d0235490136ef9f4953b7ee453073794bcaf153d20a64544ea",
"createdDate": "2020-01-14T08:46:35Z",
"createdBy": "Yeshi, Chetan",
"fileName": "Desert.jpg",
"fileType": "image/jpeg",
"id": "a092i000000M2AoAAK",
"isArchived": false,
"isDeprecated": false,
"isPrivate": true,
"lastModifiedDate": "2020-01-14T08:48:30Z",
"link": "https://access.qa.redhat.com/hydra/rest/cases/02426880/attachments/da3ccd10-b204-4688-9009-01fd0710d448",
"modifiedBy": "Yeshi, Chetan",
"size": 845941,
"sizeKB": 826.11,
"downloadRestricted": false
},
{
"caseNumber": "02426880",
"uuid": "ec95e162-3bc7-4c49-9005-bdb0ae854c0c",
"checksum": "790c7f6a905819fa49d5883ebb98cd79f4ecf9935d7d81b47e0fe24821406ca5",
"createdDate": "2020-01-14T08:44:38Z",
"createdBy": "Yeshi, Chetan",
"fileName": "f2.txt",
"fileType": "application/octet-stream",
"id": "a092i000000M2AjAAK",
"isArchived": false,
"isDeprecated": false,
"isPrivate": false,
"lastModifiedDate": "2020-01-14T08:44:38Z",
"link": "https://access.qa.redhat.com/hydra/rest/cases/02426880/attachments/ec95e162-3bc7-4c49-9005-bdb0ae854c0c",
"modifiedBy": "Yeshi, Chetan",
"size": 12000000,
"sizeKB": 11718.75,
"downloadRestricted": false
},
{
"caseNumber": "02426880",
"uuid": "ff682455-8473-4deb-8c5d-31fb8cd48679",
"checksum": "ba79e0f7d7e7045a739b20936e06873bab3a3f96eb1b6a46d6bc8a6703202a3c",
"createdDate": "2020-01-14T08:44:28Z",
"createdBy": "Yeshi, Chetan",
"description": "special_character name",
"fileName": "ChineseName_你好世界.png",
"fileType": "image/png",
"id": "a092i000000M2AZAA0",
"isArchived": false,
"isDeprecated": false,
"isPrivate": false,
"lastModifiedDate": "2020-01-14T08:44:28Z",
"link": "https://access.qa.redhat.com/hydra/rest/cases/02426880/attachments/ff682455-8473-4deb-8c5d-31fb8cd48679",
"modifiedBy": "Yeshi, Chetan",
"size": 1936056,
"sizeKB": 1890.67,
"downloadRestricted": false
},
{
"caseNumber": "02426880",
"uuid": "afc2552b-aa98-4ca9-95cb-f1638aacf1e5",
"checksum": "52f51f574956fc6b9dbc1b5ff38d18487a7593a54801803998cfb25bdedec7ba",
"createdDate": "2019-12-19T10:28:07Z",
"createdBy": "Yeshi, Chetan",
"fileName": "sosreport-3050.tar.xz",
"fileType": "application/x-xz",
"id": "a092i000000LZ0AAAW",
"isArchived": false,
"isDeprecated": false,
"isPrivate": false,
"lastModifiedDate": "2019-12-19T10:28:07Z",
"link": "https://access.qa.redhat.com/hydra/rest/cases/02426880/attachments/afc2552b-aa98-4ca9-95cb-f1638aacf1e5",
"modifiedBy": "Yeshi, Chetan",
"size": 272900344,
"sizeKB": 266504.24,
"downloadRestricted": false
},
{
"caseNumber": "02426880",
"uuid": "3ee1bad0-99a6-4880-92fa-5b16c1399a34",
"checksum": "aeb25159dc51b3e0fce4f11aa093d37df6b4372ecb41ac2a17ed8998567280a2",
"createdDate": "2019-12-19T10:27:19Z",
"createdBy": "Yeshi, Chetan",
"fileName": "sosreport-localhost.localdomain-20171016215602.tar.xz",
"fileType": "application/x-xz",
"id": "a092i000000LZ05AAG",
"isArchived": false,
"isDeprecated": false,
"isPrivate": false,
"lastModifiedDate": "2019-12-19T10:27:19Z",
"link": "https://access.qa.redhat.com/hydra/rest/cases/02426880/attachments/3ee1bad0-99a6-4880-92fa-5b16c1399a34",
"modifiedBy": "Yeshi, Chetan",
"size": 4643872,
"sizeKB": 4535.03,
"downloadRestricted": false
}
]
